ansible_galaxy_helper/__init__.py
ansible_galaxy_helper-0.1.0.dist-info/METADATA
ansible_galaxy_helper-0.1.0.dist-info/WHEEL
ansible_galaxy_helper-0.1.0.dist-info/top_level.txt
ansible_galaxy_helper-0.1.0.dist-info/RECORD
